README.rst
setup.cfg
setup.py
PyFileMaker/FMData.py
PyFileMaker/FMError.py
PyFileMaker/FMResultset.py
PyFileMaker/FMServer.py
PyFileMaker/FMXML.py
PyFileMaker/UnicodeNormalizer.py
PyFileMaker/__init__.py
PyFileMaker/xml2obj.py
PyFileMaker.egg-info/PKG-INFO
PyFileMaker.egg-info/SOURCES.txt
PyFileMaker.egg-info/dependency_links.txt
PyFileMaker.egg-info/requires.txt
PyFileMaker.egg-info/top_level.txt