Metadata-Version: 1.1
Name: PyFileMaker
Version: 3.1
Summary: Python Object Wrapper for FileMaker Server XML Interface
Home-page: https://github.com/aeguana/PyFileMaker
Author: Klokan Petr Pridal, Pieter Claerhout, Marcin Kawa
Author-email: klokan@klokan.cz, pieter@yellowduck.be, kawa.macin@gmail.com
License: http://www.opensource.org/licenses/bsd-license.php
Download-URL: https://github.com/aeguana/PyFileMaker/releases
Keywords: FileMaker
Platform: any
Classifier: Development Status :: 4 - Beta
Classifier: Environment :: Console
Classifier: Intended Audience :: Developers
Classifier: Intended Audience :: System Administrators
Classifier: License :: OSI Approved :: BSD License
Classifier: Programming Language :: Python :: 2.6
Classifier: Programming Language :: Python :: 2.7
Classifier: Topic :: Database :: Database Engines/Servers
Classifier: Topic :: Software Development :: Libraries :: Python Modules
